asrtt.py
configstore.py
utils.py
asrtt-1.3.2.dist-info/LICENSE
asrtt-1.3.2.dist-info/METADATA
asrtt-1.3.2.dist-info/WHEEL
asrtt-1.3.2.dist-info/entry_points.txt
asrtt-1.3.2.dist-info/top_level.txt
asrtt-1.3.2.dist-info/RECORD
